libMyCarrier/__init__.py
libMyCarrier/error.py
libMyCarrier/test_error.py
libMyCarrier/db/__init__.py
libMyCarrier/db/db.py
libMyCarrier/db/test_db.py
libMyCarrier/git/__init__.py
libMyCarrier/git/github.py
libMyCarrier/git/test_github.py
libMyCarrier/messages/__init__.py
libMyCarrier/messages/kafka.py
libMyCarrier/messages/test_kafka.py
libMyCarrier/secrets/__init__.py
libMyCarrier/secrets/test_vault.py
libMyCarrier/secrets/vault.py
libMyCarrier/storage/__init__.py
libMyCarrier/storage/blob.py
libMyCarrier/storage/test_blob.py
libMyCarrier/utilities/__init__.py
libMyCarrier/utilities/cistatusupdater.py
libMyCarrier/utilities/message.py
libMyCarrier/utilities/tags.py
libMyCarrier/utilities/test_cistatusupdater.py
libMyCarrier/utilities/test_message.py
libMyCarrier/utilities/test_tags.py
libmycarrier-0.4.12.dist-info/licenses/LICENSE
libmycarrier-0.4.12.dist-info/METADATA
libmycarrier-0.4.12.dist-info/WHEEL
libmycarrier-0.4.12.dist-info/entry_points.txt
libmycarrier-0.4.12.dist-info/top_level.txt
libmycarrier-0.4.12.dist-info/RECORD
