Metadata-Version: 2.4
Name: libMyCarrier
Version: 0.4.12
Author-email: MyCarrier-DevOps <sre@mycarrier.io>
License: MIT License
Project-URL: Repository, https://github.com/MyCarrier-DevOps/libMyCarrier.git
License-File: LICENSE
Requires-Dist: hvac>=2.2.0
Requires-Dist: pyodbc>=5.1.0
Requires-Dist: azure-identity>=1.16.0
Requires-Dist: snowflake-connector-python>=3.11.0
Requires-Dist: azure-storage-blob>=12.22.0
Requires-Dist: cloudevents>=1.11.0
Requires-Dist: clickhouse-connect>=0.8.14
Requires-Dist: kafka-python-ng~=2.2.3
Provides-Extra: dev
Requires-Dist: python-dotenv>=1.0.0; extra == "dev"
Requires-Dist: pytest>=7.0.0; extra == "dev"
Requires-Dist: black>=23.0.0; extra == "dev"
Requires-Dist: isort>=5.12.0; extra == "dev"
Requires-Dist: flake8>=6.0.0; extra == "dev"
Requires-Dist: mypy>=1.0.0; extra == "dev"
Dynamic: license-file
